{
 "url": "/sales-ticket-view.html?ticket=1501159",
 "docTitle": "Ticket View — WashCentral",
 "h1": [],
 "h2": [
  "Still there?"
 ],
 "h3": [],
 "breadcrumb": [
  "Transactions›Ticket View"
 ],
 "railButtons": [],
 "sidebarItems": [
  "Tickets",
  "Ticket Details",
  "Payments",
  "Refund Approvals",
  "Payouts",
  "Shifts",
  "Declined Credit Card Log",
  "Gift Card Transactions",
  "House Account Transactions"
 ],
 "buttons": [
  "Search ⌘K",
  "Ask Shyne",
  "MG",
  "← Back to Tickets",
  "Refund",
  "Main",
  "Details",
  "Payments",
  "Refunds",
  "Notes",
  "Stay Logged In",
  "Log Out Now",
  "Stay Active"
 ],
 "tabs": [
  "Main",
  "Details",
  "Payments",
  "Refunds",
  "Notes"
 ],
 "tableHeaders": [],
 "kpiLabels": [
  "$0.00Ticket Total $213.49Payments Paid / Not WashedStatus CashPayment Type",
  "$0.00Ticket Total",
  "$0.00",
  "Ticket Total",
  "$213.49Payments",
  "$213.49",
  "Payments",
  "Paid / Not WashedStatus",
  "Paid / Not Washed",
  "Status",
  "CashPayment Type",
  "Cash",
  "Payment Type"
 ],
 "inputPlaceholders": [
  "Search pages, modules, actions…"
 ],
 "labels": [],
 "chips": [],
 "firstRows": [],
 "modals": [],
 "bodySnippet": "Skip to main content MG WASHCENTRAL Sales Tickets Ticket Details Payments Refund Approvals Payouts Shifts Declined Credit Card Log Gift Card Transactions House Account Transactions TRANSACTIONS Ticket View Search ⌘K Ask Shyne MG Shift28753 Sales · Ticket · ID: 1501159 · 121 - Groveport S Hamilton · 2026-01-11 04:51 ← Back to Tickets Refund $0.00 Ticket Total $213.49 Payments Paid / Not Washed Status Cash Payment Type Main Details Payments Refunds Notes TICKET INFORMATION ID 1501159 TICKET NUMBER Shift28753 DATE/TIME IN 2026-01-11 04:51 LOCATION 121 - Groveport S Hamilton STATUS Paid / Not Washed PAYMENT TYPE Cash FINANCIAL SUMMARY TOTAL $0.00 TAXES $0.00 TENDERED $0.00 CHANGE DUE $0.00 REVERSED No HOUSE ACCOUNT No HOUSE ACCOUNT NAME — STAFF & EQUIPMENT CASHIER MOO121-VQ CASHIER CODE 521446 CASHIER TERMINAL MOO121-VQ GREETER NAME Corday Burgess GREETER TERMINAL MOO121-VQ SHIFT 28753 CUSTOMER & VEHICLE CUSTOMER — COMPANY — VEHICLE — VEHICLE PLATE — VEHICLE STATE — Loading… 2:00 REMAINING Still there? Your session will end in 2:00 due to inactivity. Move your mouse or press any key to stay logged in. Stay Logged In Log Out Now ⏱ Session expiring soon Auto-logout in 2:00 Stay Active esc ↑ ↓ Navigate ↵ Open Esc Close"
}